[
    {
        "name": "symbol",
        "type": "STRING",
        "mode": "REQUIRED",
        "description": "Stock symbol"
    },
    {
        "name": "prediction_date",
        "type": "DATE",
        "mode": "REQUIRED",
        "description": "Date when prediction was made"
    },
    {
        "name": "prediction_days",
        "type": "INTEGER",
        "mode": "REQUIRED",
        "description": "Number of days ahead predicted"
    },
    {
        "name": "current_price",
        "type": "FLOAT64",
        "mode": "REQUIRED",
        "description": "Current price when prediction was made"
    },
    {
        "name": "predicted_price",
        "type": "FLOAT64",
        "mode": "REQUIRED",
        "description": "Predicted future price"
    },
    {
        "name": "confidence_score",
        "type": "FLOAT64",
        "mode": "REQUIRED",
        "description": "Prediction confidence score (0-1)"
    },
    {
        "name": "model_version",
        "type": "STRING",
        "mode": "NULLABLE",
        "description": "ML model version used"
    },
    {
        "name": "model_type",
        "type": "STRING",
        "mode": "NULLABLE",
        "description": "Type of prediction model"
    },
    {
        "name": "prediction_horizon",
        "type": "INTEGER",
        "mode": "NULLABLE",
        "description": "Prediction time horizon in days"
    },
    {
        "name": "features_used",
        "type": "STRING",
        "mode": "NULLABLE",
        "description": "Features used in prediction (JSON)"
    },
    {
        "name": "is_active",
        "type": "BOOLEAN",
        "mode": "REQUIRED",
        "description": "Whether prediction is active"
    },
    {
        "name": "created_at",
        "type": "TIMESTAMP",
        "mode": "REQUIRED",
        "description": "Record creation timestamp"
    }
]